toxine/__init__.py
toxine/_version.py
toxine/brat.py
toxine/text_preprocessor.py
toxine/wikipedia_utils.py
toxine-1.0.52.dist-info/LICENSE
toxine-1.0.52.dist-info/METADATA
toxine-1.0.52.dist-info/WHEEL
toxine-1.0.52.dist-info/top_level.txt
toxine-1.0.52.dist-info/RECORD
