Metadata-Version: 2.1
Name: toxine
Version: 1.0.52
Summary: Tiny preprocessor for Russian text
Home-page: https://github.com/fostroll/toxine
Author: Sergei Ternovykh
Author-email: fostroll@gmail.com
License: BSD
Keywords: natural-language-processing nlp preprocessing
Platform: UNKNOWN
Classifier: Development Status :: 4 - Beta
Classifier: Intended Audience :: Developers
Classifier: Intended Audience :: Education
Classifier: Intended Audience :: Science/Research
Classifier: Intended Audience :: Information Technology
Classifier: Topic :: Scientific/Engineering
Classifier: Topic :: Scientific/Engineering :: Artificial Intelligence
Classifier: Topic :: Scientific/Engineering :: Information Analysis
Classifier: Topic :: Text Processing
Classifier: Topic :: Text Processing :: Linguistic
Classifier: Topic :: Software Development
Classifier: Topic :: Software Development :: Libraries
Classifier: Programming Language :: Python :: 3.5
Classifier: Programming Language :: Python :: 3.6
Classifier: Programming Language :: Python :: 3.7
Classifier: Programming Language :: Python :: 3.8
Requires-Python: >=3.5
Requires-Dist: corpuscula
Requires-Dist: nltk
Requires-Dist: pymorphy2
